LICENCE
MANIFEST.in
README.md
setup.cfg
setup.py
examples/__init__.py
examples/charcnn_text_classifier.py
examples/cifar10_allcnn.py
examples/example.py
examples/hierachical_softmax.py
examples/mnist_cnn.py
examples/multi_gpus_horovod.py
tensorgraph/__init__.py
tensorgraph/cost.py
tensorgraph/data_iterator.py
tensorgraph/graph.py
tensorgraph/node.py
tensorgraph/progbar.py
tensorgraph/sequential.py
tensorgraph/stopper.py
tensorgraph/trainobject.py
tensorgraph/utils.py
tensorgraph.egg-info/PKG-INFO
tensorgraph.egg-info/SOURCES.txt
tensorgraph.egg-info/dependency_links.txt
tensorgraph.egg-info/not-zip-safe
tensorgraph.egg-info/requires.txt
tensorgraph.egg-info/top_level.txt
tensorgraph/dataset/__init__.py
tensorgraph/dataset/cifar10.py
tensorgraph/dataset/cifar100.py
tensorgraph/dataset/imagenet.py
tensorgraph/dataset/mnist.py
tensorgraph/dataset/preprocess.py
tensorgraph/dataset/voc2012.py
tensorgraph/layers/__init__.py
tensorgraph/layers/activation.py
tensorgraph/layers/backbones.py
tensorgraph/layers/cast.py
tensorgraph/layers/conv.py
tensorgraph/layers/linear.py
tensorgraph/layers/merge.py
tensorgraph/layers/misc.py
tensorgraph/layers/noise.py
tensorgraph/layers/normalization.py
tensorgraph/layers/random.py
tensorgraph/layers/recurrent.py
tensorgraph/layers/template.py
tensorgraph/multi_gpus/cifar10.py
tensorgraph/multi_gpus/cifar10_input.py
tensorgraph/multi_gpus/cifar10_multi_gpu_train.py
tensorgraph/multi_gpus/data_parallel.py
tensorgraph/multi_gpus/model.py
tensorgraph/multi_gpus/test.py
tensorgraph/multi_gpus/train.py