Metadata-Version: 1.1
Name: tensorgraph
Version: 5.0.1
Summary: A high level tensorflow library for building deep learning models
Home-page: https://github.com/hycis/TensorGraph
Author: Wu Zhen Zhou
Author-email: hyciswu@gmail.com
License: Apache 2.0, see LICENCE
Download-URL: https://github.com/hycis/TensorGraph/tarball/5.0.1
Platform: UNKNOWN
